odoo/addons/mass_mailing_company_newsletter/README.rst
odoo/addons/mass_mailing_company_newsletter/__init__.py
odoo/addons/mass_mailing_company_newsletter/__manifest__.py
odoo/addons/mass_mailing_company_newsletter/i18n/mass_mailing_company_newsletter.pot
odoo/addons/mass_mailing_company_newsletter/models/__init__.py
odoo/addons/mass_mailing_company_newsletter/models/res_company.py
odoo/addons/mass_mailing_company_newsletter/models/res_config_settings.py
odoo/addons/mass_mailing_company_newsletter/models/res_partner.py
odoo/addons/mass_mailing_company_newsletter/readme/CONFIGURE.rst
odoo/addons/mass_mailing_company_newsletter/readme/CONTRIBUTORS.rst
odoo/addons/mass_mailing_company_newsletter/readme/DESCRIPTION.rst
odoo/addons/mass_mailing_company_newsletter/static/description/icon.png
odoo/addons/mass_mailing_company_newsletter/static/description/index.html
odoo/addons/mass_mailing_company_newsletter/tests/__init__.py
odoo/addons/mass_mailing_company_newsletter/tests/test_company_newsletter.py
odoo/addons/mass_mailing_company_newsletter/views/res_config_settings.xml
odoo/addons/mass_mailing_company_newsletter/views/res_partner.xml
odoo14_addon_mass_mailing_company_newsletter-14.0.1.0.1.dist-info/METADATA
odoo14_addon_mass_mailing_company_newsletter-14.0.1.0.1.dist-info/WHEEL
odoo14_addon_mass_mailing_company_newsletter-14.0.1.0.1.dist-info/top_level.txt
odoo14_addon_mass_mailing_company_newsletter-14.0.1.0.1.dist-info/RECORD
