Metadata-Version: 2.1
Name: odoo14-addon-mass-mailing-company-newsletter
Version: 14.0.1.0.1
Summary: Easily manage partner's subscriptions to your main mailing list.
Home-page: https://github.com/OCA/social
Author: Camptocamp, Odoo Community Association (OCA)
Author-email: support@odoo-community.org
License: AGPL-3
Platform: UNKNOWN
Classifier: Programming Language :: Python
Classifier: Framework :: Odoo
Classifier: Framework :: Odoo :: 14.0
Classifier: License :: OSI Approved :: GNU Affero General Public License v3
Requires-Python: >=3.6
Requires-Dist: odoo14-addon-mass-mailing-contact-partner
Requires-Dist: odoo14-addon-mass-mailing-subscription-date
Requires-Dist: odoo (<14.1dev,>=14.0a)
